wulffpack/__init__.py
wulffpack/decahedron.py
wulffpack/icosahedron.py
wulffpack/single_crystal.py
wulffpack/winterbottom.py
wulffpack/core/__init__.py
wulffpack/core/base_particle.py
wulffpack/core/facet.py
wulffpack/core/form.py
wulffpack/core/geometry.py
wulffpack-1.5.dist-info/licenses/LICENSE
wulffpack-1.5.dist-info/METADATA
wulffpack-1.5.dist-info/WHEEL
wulffpack-1.5.dist-info/top_level.txt
wulffpack-1.5.dist-info/RECORD
