Metadata-Version: 2.4
Name: wulffpack
Version: 1.5
Summary: A package for making Wulff constructions
Author: J. Magnus Rahm, Paul Erhart
Maintainer: The WulffPack developer team
License: Mozilla Public License Version 2.0
Project-URL: Documentation, https://wulffpack.materialsmodeling.org
Project-URL: Repository, https://gitlab.com/materials-modeling/wulffpack/
Keywords: chemistry,physics,scientific
Classifier: Development Status :: 5 - Production/Stable
Classifier: Operating System :: OS Independent
Classifier: Programming Language :: Python :: 3 :: Only
Classifier: Programming Language :: Python :: 3
Classifier: Programming Language :: Python :: 3.9
Classifier: Programming Language :: Python :: 3.10
Classifier: Programming Language :: Python :: 3.11
Classifier: Programming Language :: Python :: 3.12
Classifier: Programming Language :: Python :: 3.13
Classifier: Intended Audience :: Education
Classifier: Intended Audience :: Science/Research
Classifier: Programming Language :: Python
Classifier: Topic :: Scientific/Engineering :: Physics
Requires-Python: >=3.9
License-File: LICENSE
Requires-Dist: ase
Requires-Dist: numpy>=1.12
Requires-Dist: scipy>=0.12.0
Requires-Dist: spglib
Requires-Dist: matplotlib
Provides-Extra: test
Requires-Dist: flake8; extra == "test"
Requires-Dist: coverage; extra == "test"
Requires-Dist: pytest; extra == "test"
Requires-Dist: xdoctest; extra == "test"
Provides-Extra: documentation
Requires-Dist: sphinx_autodoc_typehints; extra == "documentation"
Requires-Dist: sphinx-sitemap; extra == "documentation"
Requires-Dist: sphinx_rtd_theme; extra == "documentation"
Requires-Dist: pydata-sphinx-theme; extra == "documentation"
Dynamic: license-file
